revalorise
